<GeoServerTileLayer>
  <id>LayerInfoImpl--1df5162f:165a98b553c:-7fce</id>
  <enabled>true</enabled>
  <inMemoryCached>true</inMemoryCached>
  <name>vt:UtilityInfrastructurePnt</name>
  <mimeFormats>
    <string>image/png</string>
    <string>image/jpeg</string>
    <string>application/json;type=geojson</string>
    <string>application/json;type=topojson</string>
    <string>application/x-protobuf;type=mapbox-vector</string>
  </mimeFormats>
  <gridSubsets>
    <gridSubset>
      <gridSetName>EPSG:4326</gridSetName>
      <extent>
        <coords>
          <double>36.04500839346683</double>
          <double>32.58893782372647</double>
          <double>36.13385932091463</double>
          <double>32.654391018218554</double>
        </coords>
      </extent>
    </gridSubset>
    <gridSubset>
      <gridSetName>EPSG:900913</gridSetName>
      <extent>
        <coords>
          <double>4012511.9799999995</double>
          <double>3840868.579999997</double>
          <double>4022402.8199999984</double>
          <double>3849519.4899999984</double>
        </coords>
      </extent>
    </gridSubset>
  </gridSubsets>
  <metaWidthHeight>
    <int>4</int>
    <int>4</int>
  </metaWidthHeight>
  <expireCache>0</expireCache>
  <expireClients>0</expireClients>
  <parameterFilters>
    <styleParameterFilter>
      <key>STYLES</key>
      <defaultValue></defaultValue>
      <availableStyles class="sorted-set"/>
      <defaultStyle>point</defaultStyle>
    </styleParameterFilter>
  </parameterFilters>
  <gutter>0</gutter>
</GeoServerTileLayer>